[
    {
      "Name": "Misty Fist",
      "Class": "Rogue",
      "ID": null,
      "Description": "Deals 299 damage. Delivers a steady two-handed blow.",
      "Lore": null,
      "Level": 30,
      "Type": "Physical",
      "CastTime": "1 second",
      "Vigor Cost": null,
      "ManaCost": 90,
      "CoolDown": null,
      "Duration": null
    },
    {
      "Name": "Snarling Strike",
      "Class": "Rogue",
      "ID": null,
      "Description": "Deals 243 damage. Aim low and strike deep.",
      "Lore": "",
      "Level": 30,
      "Type": "Ferus Spell",
      "CastTime": "1 second",
      "Vigor Cost": null,
      "ManaCost": 71,
      "CoolDown": "3 seconds",
      "Duration": null
    },
    {
      "Name": "Inner Mountain Flame",
      "Class": "Rogue",
      "ID": null,
      "Description": "Adds 10 Strength. Adds 200 to Max Health.",
      "Lore": "Run wild! Call upon the wolf spirits for increased movement speed. (Cannot use while invisible)",
      "Level": 5,
      "Type": "Passive",
      "CastTime": null,
      "Vigor Cost": null,
      "ManaCost": null,
      "CoolDown": null,
      "Duration": null
    },
    {
      "Name": "Vicious Wish",
      "Class": "Rogue",
      "ID": null,
      "Description": "Adds 50% to Critstrike. Adds 50% to Critcast.",
      "Lore": null,
      "Level": 5,
      "Type": null,
      "CastTime": "1 second",
      "Vigor Cost": null,
      "ManaCost": 149,
      "CoolDown": "30 seconds",
      "Duration": "10 seconds"
    },
    {
      "Name": "Wolf Sprint",
      "Class": "Rogue",
      "ID": null,
      "Description": "Temporarily increase movement speed by 2.0. Lasts 20 seconds.",
      "Lore": null,
      "Level": 5,
      "Type": null,
      "CastTime": "2 seconds",
      "Vigor Cost": null,
      "ManaCost": 356,
      "CoolDown": "60 seconds",
      "Duration": "20 seconds"
    },
    {
      "Name": "Blade of the Crimson Lotus",
      "Class": "Rogue",
      "ID": null,
      "Description": "Deals 470 damage. Has a 50% chance to Daze target for 3 seconds.",
      "Lore": null,
      "Level": 20,
      "Type": "Ferus Spell",
      "CastTime": "1 second",
      "Vigor Cost": null,
      "ManaCost": 355,
      "CoolDown": "20 seconds",
      "Duration": null
    },
    {
      "Name": "Soulcrack Moonfist",
      "Class": "Rogue",
      "ID": null,
      "Description": "Deals 833 damage.",
      "Lore": "The essence of violence. Lace your blade with the vengence of hell. (Cannot use while invisible)",
      "Level": 20,
      "Type": "Ferus Spell",
      "CastTime": "2 seconds",
      "Vigor Cost": null,
      "ManaCost": 290,
      "CoolDown": "3 seconds",
      "Duration": null
    },
    {
      "Name": "Dust in the Wind",
      "Class": "Rogue",
      "ID": null,
      "Description": "become invisible. Movement speed is reduced. While effect lasts one is unable to eat, drink, or cast certain spells.",
      "Lore": "(Use while effect is already active to cancel)",
      "Level": 10,
      "Type": null,
      "CastTime": "1 second",
      "Vigor Cost": null,
      "ManaCost": 1160,
      "CoolDown": "60 seconds",
      "Duration": "300 seconds"
    },
    {
      "Name": "Vile Blessing",
      "Class": "Rogue",
      "ID": null,
      "Description": "Poison target, reducing its maximum Health by 20%. Every 2 seconds drains 10% of target's max MP. Lasts 21 seconds.",
      "Lore": "Dust Cost: 2 Ferus Dust. (Cannot use while invisible)",
      "Level": 10,
      "Type": "Ferus Curse",
      "CastTime": "1 second",
      "Vigor Cost": null,
      "ManaCost": 549,
      "CoolDown": "30 seconds",
      "Duration": null
    },
    {
      "Name": "Netheryn Bloodkiss",
      "Class": "Rogue",
      "ID": null,
      "Description": "Coat your blades with vile poison. Effect lasts 330 seconds. Your attacks have a chance to poison target. Poisoned target will lose up to 6% of Max Health every 3 seconds. Lasts 31 seconds.",
      "Lore": "Element Dust Cost: 4 Ferus Dust",
      "Level": 10,
      "Type": null,
      "CastTime": "1 second",
      "Vigor Cost": null,
      "ManaCost": 1783,
      "CoolDown": "5 seconds",
      "Duration": null
    },
    {
      "Name": "Glaive of Ill Will",
      "Class": "Rogue",
      "ID": null,
      "Description": "Attack target for 100% of base damage. Also has 70% chance to Silence target for 5 seconds!",
      "Lore": null,
      "Level": 10,
      "Type": "Ferus Spell",
      "CastTime": "1 second",
      "Vigor Cost": null,
      "ManaCost": 1073,
      "CoolDown": "60 seconds",
      "Duration": null
    },
    {
      "Name": "Felblade Chisel",
      "Class": "Rogue",
      "ID": null,
      "Description": "Critstrike chance increased by 10%. Critcast chance increased by 10%.",
      "Lore": null,
      "Level": "",
      "Type": "Passive",
      "CastTime": null,
      "Vigor Cost": null,
      "ManaCost": null,
      "CoolDown": null,
      "Duration": null
    },
    {
      "Name": "Way of the Soul Tyrant",
      "Class": "Rogue",
      "ID": null,
      "Description": "STR + 1000, INT +1000. Immune to Sleep and Stun for 40 seconds. Also Ferus Affinity is increased by 40 for 260 seconds. Passively reduces Bloodmoon's Eve Cooldown to 60 seconds. Passively reduces The Abyss' Cooldown to 30 seconds.",
      "Lore": null,
      "Level": 5,
      "Type": "Self Blessing",
      "CastTime": "1 second",
      "Vigor Cost": null,
      "ManaCost": 1375,
      "CoolDown": "60 seconds",
      "Duration": null
    },
    {
      "Name": "Instant Thunder",
      "Class": "Rogue",
      "ID": null,
      "Description": "Has a 80% chance to sleep target for 40 seconds.",
      "Lore": "(Sleeping targets are revived upon attack)",
      "Level": 5,
      "Type": "Ferus Curse",
      "CastTime": "1 second",
      "Vigor Cost": null,
      "ManaCost": 999,
      "CoolDown": "60 seconds",
      "Duration": null
    },
    {
      "Name": "Golden Mean",
      "Class": "Rogue",
      "ID": null,
      "Description": "Critstrike chance increased by 10% with this skill. First strike deals and extra 660 damage. Second strike deals and extra (Acc*10) damage.",
      "Lore": null,
      "Level": 5,
      "Type": "Ferus Dual Attack",
      "CastTime": "2 seconds",
      "Vigor Cost": null,
      "ManaCost": 3399,
      "CoolDown": "30 seconds",
      "Duration": null
    },
    {
      "Name": "Blessed Samsara",
      "Class": "Rogue",
      "ID": null,
      "Description": "Enters Samsara state. Become invisible. Speed increased by 2.0. Dispels all movement impairing effects. Lasts 60 seconds. Effect canceled if you attack, cast spells, or are attacked!",
      "Lore": null,
      "Level": 5,
      "Type": "Self Blessing",
      "CastTime": "1 second",
      "Vigor Cost": null,
      "ManaCost": 2034,
      "CoolDown": "60 seconds",
      "Duration": null
    },
    {
      "Name": "Void Cleave",
      "Class": "Rogue",
      "ID": null,
      "Description": "Affects 15 targets within a cone shape towards target. Deals 100% of attack power.",
      "Lore": "(Cannot be used while invisible)",
      "Level": 5,
      "Type": "Ferus Spell",
      "CastTime": "1 second",
      "Vigor Cost": null,
      "ManaCost": 263,
      "CoolDown": "1 second",
      "Duration": null
    },
    {
      "Name": "Shady Blade",
      "Class": "Rogue",
      "ID": null,
      "Description": "Deals 435 damage.",
      "Lore": "(Cannot use while invisible)",
      "Level": 5,
      "Type": "Ferus Spell",
      "CastTime": "2 seconds",
      "Vigor Cost": null,
      "ManaCost": 151,
      "CoolDown": "3 seconds",
      "Duration": null
    },
    {
      "Name": "Bloodmoon's Eve",
      "Class": "Rogue",
      "ID": null,
      "Description": "Affects nearby foes within 7 yards of caster. Up to 10 foes have a 80% chance for the next 6 seconds to be Ferus Silenced.",
      "Lore": "Prevents all affected units from casting Ferus spells. (Cannot use while invisible)",
      "Level": 5,
      "Type": "Ferus Curse",
      "CastTime": "2 seconds",
      "Vigor Cost": 10,
      "ManaCost": 948,
      "CoolDown": "300 seconds",
      "Duration": null
    },
    {
      "Name": "Kinetic Blast",
      "Class": "Rogue",
      "ID": null,
      "Description": "Deals 450 damage. Has a 60% chance to Sleep target for 3 seconds!",
      "Lore": "(Can only be used while invisible)",
      "Level": 5,
      "Type": "Ferus Spell",
      "CastTime": "1 second",
      "Vigor Cost": null,
      "ManaCost": 340,
      "CoolDown": "30 seconds",
      "Duration": null
    },
    {
      "Name": "Vilewind Blow",
      "Class": "Rogue",
      "ID": null,
      "Description": "Initial strike deals 1043 damage. The second strike adds 50% of normal damage plus 521. The third strike deals 100% of normal damage plus 550.",
      "Lore": "(Cannot use while invisible)",
      "Level": 5,
      "Type": "Ferus Spell",
      "CastTime": "3 seconds",
      "Vigor Cost": 30,
      "ManaCost": 1681,
      "CoolDown": "60 seconds",
      "Duration": null
    },
    {
      "Name": "The Abyss",
      "Class": "Rogue",
      "ID": null,
      "Description": "Has a 80% chance to Blind target for 10 seconds!",
      "Lore": "(Cannot be used while invisible)",
      "Level": 5,
      "Type": null,
      "CastTime": "1 second",
      "Vigor Cost": null,
      "ManaCost": 4070,
      "CoolDown": "60 seconds",
      "Duration": null
    },
    {
      "Name": "Featherwind Split",
      "Class": "Ranger",
      "ID": null,
      "Description": "Deals 281 damage",
      "Lore": null,
      "Level": 30,
      "Type": "Physical",
      "CastTime": "1 second",
      "Vigor Cost": null,
      "ManaCost": 101,
      "CoolDown": "0 seconds",
      "Duration": null
    },
    {
      "Name": "Stardrop Hymn",
      "Class": "Ranger",
      "ID": null,
      "Description": "Adds 5 to pet Affinity",
      "Lore": null,
      "Level": 5,
      "Type": "Passive",
      "CastTime": null,
      "Vigor Cost": null,
      "ManaCost": null,
      "CoolDown": null,
      "Duration": null
    },
    {
      "Name": "Archer's Alarcity",
      "Class": "Ranger",
      "ID": null,
      "Description": "Deals 39 damage",
      "Lore": null,
      "Level": 5,
      "Type": "Flora Spell",
      "CastTime": "1 second",
      "Vigor Cost": null,
      "ManaCost": 16,
      "CoolDown": "3 seconds",
      "Duration": null
    },
    {
      "Name": "Weathered Resolve",
      "Class": "Ranger",
      "ID": null,
      "Description": "Adds 10 to Defense. Increases Mac Health by 400.",
      "Lore": null,
      "Level": 5,
      "Type": "Passive",
      "CastTime": null,
      "Vigor Cost": null,
      "ManaCost": null,
      "CoolDown": null,
      "Duration": null
    },
    {
      "Name": "Undan Arrow",
      "Class": "Ranger",
      "ID": null,
      "Description": "Deals 300 damage",
      "Lore": null,
      "Level": 30,
      "Type": "Unda Spell",
      "CastTime": "1 second",
      "Vigor Cost": null,
      "ManaCost": 82,
      "CoolDown": "3 seconds",
      "Duration": null
    },
    {
      "Name": "Tainted Dreamshot",
      "Class": "Ranger",
      "ID": null,
      "Description": "Deals 464 damage. Has a 60% chance to put target to Sleep for 6 seconds.",
      "Lore": "(Sleeping target will be aroused when attacked)",
      "Level": 30,
      "Type": "Flora Spell",
      "CastTime": "1 second",
      "Vigor Cost": null,
      "ManaCost": 419,
      "CoolDown": "15 seconds",
      "Duration": null
    },
    {
      "Name": "Instill Essence",
      "Class": "Ranger",
      "ID": null,
      "Description": "Adds 31 Strength. Adds 31 Intelligence. Lasts 30 minutes.",
      "Lore": null,
      "Level": 10,
      "Type": null,
      "CastTime": "1 second",
      "Vigor Cost": null,
      "ManaCost": 387,
      "CoolDown": "30 seconds",
      "Duration": null
    },
    {
      "Name": "Searing Glance",
      "Class": "Ranger",
      "ID": null,
      "Description": "Deals 374 damage. Has 50% chance to Slow target for 16 seconds.",
      "Lore": "(Cannot use during combat)",
      "Level": 10,
      "Type": "Aquan Spell",
      "CastTime": "1 second",
      "Vigor Cost": null,
      "ManaCost": 334,
      "CoolDown": "30 seconds",
      "Duration": null
    },
    {
      "Name": "Solidarity",
      "Class": "Ranger",
      "ID": null,
      "Description": "Radius: 20 yards. All friendly units within range of 10 receive 20 bonus Accuracy points. Lasts 20 seconds.",
      "Lore": null,
      "Level": 10,
      "Type": null,
      "CastTime": "2 seconds",
      "Vigor Cost": null,
      "ManaCost": 839,
      "CoolDown": "30 seconds",
      "Duration": null
    },
    {
      "Name": "Ode to the Hunted",
      "Class": "Ranger",
      "ID": null,
      "Description": "Raises Pet Affinity by 20. Lasts 1800 seconds.",
      "Lore": null,
      "Level": 10,
      "Type": null,
      "CastTime": "2 seconds",
      "Vigor Cost": null,
      "ManaCost": 2058,
      "CoolDown": "5 seconds",
      "Duration": null
    },
    {
      "Name": "Curse of Lethargy",
      "Class": "Ranger",
      "ID": null,
      "Description": "Summons an evil bog under your target. Random players or monsters within this bog, will be put to sleep every 3 seconds. Bog remains for 20 seconds.",
      "Lore": "(Sleeping targets will wake up if damaged.)",
      "Level": 10,
      "Type": null,
      "CastTime": "2 seconds",
      "Vigor Cost": null,
      "ManaCost": 2478,
      "CoolDown": "300 seconds",
      "Duration": null
    },
    {
      "Name": "Heaven's Gaze",
      "Class": "Ranger",
      "ID": null,
      "Description": "Accuracy increased by 60",
      "Lore": null,
      "Level": 5,
      "Type": "Passive",
      "CastTime": null,
      "Vigor Cost": null,
      "ManaCost": null,
      "CoolDown": null,
      "Duration": null
    },
    {
      "Name": "Holy Grasp",
      "Class": "Ranger",
      "ID": null,
      "Description": "Targets in flight have an 80% chance to be grounded for 10 seconds.",
      "Lore": null,
      "Level": 5,
      "Type": "Flora Curse",
      "CastTime": "2 seconds",
      "Vigor Cost": null,
      "ManaCost": 1110,
      "CoolDown": "30 seconds",
      "Duration": null
    },
    {
      "Name": "Lucky Bowstring",
      "Class": "Ranger",
      "ID": null,
      "Description": "Increases your attack range for 40 seconds. Weapon range increased by 5 yards. Increases Flora Affinity by 40. Lasts for 300 seconds.",
      "Lore": null,
      "Level": 5,
      "Type": "Self Blessing",
      "CastTime": "1 second",
      "Vigor Cost": null,
      "ManaCost": 1647,
      "CoolDown": "120 seconds",
      "Duration": null
    },
    {
      "Name": "Sky Drop",
      "Class": "Ranger",
      "ID": null,
      "Description": "When using this skill, Critcast chance increased by 10%. First strike adds 638 damage. Second strike adds (RESL*15) damage.",
      "Lore": null,
      "Level": 5,
      "Type": "Aquan Dual Attack",
      "CastTime": "2 seconds",
      "Vigor Cost": null,
      "ManaCost": 3922,
      "CoolDown": "30 seconds",
      "Duration": null
    },
    {
      "Name": "Nine Soul Erosion",
      "Class": "Ranger",
      "ID": null,
      "Description": "Has an 80% chance to cancel target's Pet's Fusion, and prevent fusion for 20 seconds.",
      "Lore": null,
      "Level": 5,
      "Type": "Flora Curse",
      "CastTime": "1 second",
      "Vigor Cost": null,
      "ManaCost": 2347,
      "CoolDown": "60 seconds",
      "Duration": null
    },
    {
      "Name": "Surprise Assault",
      "Class": "Ranger",
      "ID": null,
      "Description": "Casts in a cone shape hitting 15 enemies in front of the caster. Inflicts 100% of attack damage to primary target.",
      "Lore": null,
      "Level": 5,
      "Type": "Aquan Spell",
      "CastTime": "1 second",
      "Vigor Cost": null,
      "ManaCost": 263,
      "CoolDown": "1 second",
      "Duration": null
    },
    {
      "Name": "Ancestral Arrow",
      "Class": "Ranger",
      "ID": null,
      "Description": "Simultaneously attack 10 targets dealing 228 damage.",
      "Lore": null,
      "Level": 5,
      "Type": "Aquan Spell",
      "CastTime": "3 seconds",
      "Vigor Cost": null,
      "ManaCost": 703,
      "CoolDown": "60 seconds",
      "Duration": null
    },
    {
      "Name": "Gravitas",
      "Class": "Ranger",
      "ID": null,
      "Description": "Adds 664 damage. Has 80% chance to Slow target for 6 seconds.",
      "Lore": null,
      "Level": 5,
      "Type": "Flora Spell",
      "CastTime": "3 seconds",
      "Vigor Cost": 10,
      "ManaCost": 272,
      "CoolDown": "30 seconds",
      "Duration": null
    },
    {
      "Name": "One for the Vine",
      "Class": "Ranger",
      "ID": null,
      "Description": "Inflicts 70% of base damage. Has 50% chance to Ensnare target for 3 seconds.",
      "Lore": null,
      "Level": 5,
      "Type": "Flora Spell",
      "CastTime": "1 second",
      "Vigor Cost": null,
      "ManaCost": 392,
      "CoolDown": "30 seconds",
      "Duration": null
    },
    {
      "Name": "Fallen Star",
      "Class": "Ranger",
      "ID": null,
      "Description": "Initial attack deals 962 of basse damage. Second attack deals 50% of base damage, plus 480. Third attack deals 100% of base damage, plus 530.",
      "Lore": "(Can only be used while under the effects of Solidarity)",
      "Level": 5,
      "Type": "Aquan Spell",
      "CastTime": "3 seconds",
      "Vigor Cost": 30,
      "ManaCost": 1939,
      "CoolDown": "60 seconds",
      "Duration": null
    },
    {
      "Name": "Wings of Freedom",
      "Class": "Ranger",
      "ID": null,
      "Description": "Use for a 65% chance to break free from all that impedes you.",
      "Lore": null,
      "Level": 5,
      "Type": null,
      "CastTime": "1 second",
      "Vigor Cost": null,
      "ManaCost": 2347,
      "CoolDown": "60 seconds",
      "Duration": null
    },
    {
      "Name": "Banewind Gust",
      "Class": "Dragoon",
      "ID": null,
      "Description": "Deals 268 damage",
      "Lore": null,
      "Level": 30,
      "Type": "Physical",
      "CastTime": "1 second",
      "Vigor Cost": null,
      "ManaCost": 81,
      "CoolDown": "0 seconds",
      "Duration": null
    },
    {
      "Name": "Void Bubble",
      "Class": "Dragoon",
      "ID": null,
      "Description": "Increases Max Health by 956. Lasts 360 seconds.",
      "Lore": null,
      "Level": 30,
      "Type": null,
      "CastTime": "2 seconds",
      "Vigor Cost": null,
      "ManaCost": 829,
      "CoolDown": "30 seconds",
      "Duration": null
    },
    {
      "Name": "Bengal Heart",
      "Class": "Dragoon",
      "ID": null,
      "Description": "Adds 10 Strength. Adds 200 to Max Health.",
      "Lore": null,
      "Level": 5,
      "Type": "Passive",
      "CastTime": null,
      "Vigor Cost": null,
      "ManaCost": null,
      "CoolDown": null,
      "Duration": null
    },
    {
      "Name": "Liger Skitt",
      "Class": "Dragoon",
      "ID": null,
      "Description": "Deals 46 damage.",
      "Lore": null,
      "Level": 5,
      "Type": "Terra Spell",
      "CastTime": "1 second",
      "Vigor Cost": null,
      "ManaCost": 18,
      "CoolDown": "3 seconds",
      "Duration": null
    },
    {
      "Name": "Sleep Monkey, Sleep",
      "Class": "Dragoon",
      "ID": null,
      "Description": "Deals 276 damage. Has a 60% chance to put target to Sleep for 3 seconds.",
      "Lore": null,
      "Level": 30,
      "Type": "Terra Spell",
      "CastTime": "1 second",
      "Vigor Cost": null,
      "ManaCost": 65,
      "CoolDown": "10 seconds",
      "Duration": null
    },
    {
      "Name": "Burning Spear",
      "Class": "Dragoon",
      "ID": null,
      "Description": "Deals 610 damage.",
      "Lore": null,
      "Level": 30,
      "Type": "Terra Spell",
      "CastTime": "1.5 seconds",
      "Vigor Cost": null,
      "ManaCost": 335,
      "CoolDown": "2 seconds",
      "Duration": null
    },
    {
      "Name": "Snow Tiger Assault",
      "Class": "Dragoon",
      "ID": null,
      "Description": "Deals 792 damage.",
      "Lore": null,
      "Level": 25,
      "Type": "Terra Spell",
      "CastTime": "2 seconds",
      "Vigor Cost": null,
      "ManaCost": 335,
      "CoolDown": "3 seconds",
      "Duration": null
    },
    {
      "Name": "Everwood Infusion",
      "Class": "Dragoon",
      "ID": null,
      "Description": "Physical damage taken is reduced by 100%. Lasts 30 seconds.",
      "Lore": null,
      "Level": 10,
      "Type": null,
      "CastTime": "2 seconds",
      "Vigor Cost": null,
      "ManaCost": 534,
      "CoolDown": "300 seconds",
      "Duration": null
    },
    {
      "Name": "Enrage",
      "Class": "Dragoon",
      "ID": null,
      "Description": "Has effect radius of 15 yards. Up to 15 allies have their critical damage increased by 20%.",
      "Lore": null,
      "Level": 10,
      "Type": null,
      "CastTime": "1 second",
      "Vigor Cost": null,
      "ManaCost": 671,
      "CoolDown": "30 seconds",
      "Duration": "360 seconds"
    },
    {
      "Name": "Bloodance Growl",
      "Class": "Dragoon",
      "ID": null,
      "Description": "Increases Max Health by 6500. Increase Defense by 30. Lasts 600 seconds.",
      "Lore": null,
      "Level": 10,
      "Type": null,
      "CastTime": "1 second",
      "Vigor Cost": null,
      "ManaCost": 1646,
      "CoolDown": "5 seconds",
      "Duration": null
    },
    {
      "Name": "Soul Tremor",
      "Class": "Dragoon",
      "ID": null,
      "Description": "Has effect radius of 10 yards. 10 enemies within range have Strength and Intelligence reduced by 500. Lasts 15 seconds.",
      "Lore": null,
      "Level": 10,
      "Type": "Terra Curse",
      "CastTime": "2 seconds",
      "Vigor Cost": null,
      "ManaCost": 990,
      "CoolDown": "60 seconds",
      "Duration": null
    },
    {
      "Name": "Phoenix Stature",
      "Class": "Dragoon",
      "ID": null,
      "Description": "Defense increased by 250. Resistance increased by 500.",
      "Lore": null,
      "Level": 5,
      "Type": "Passive",
      "CastTime": null,
      "Vigor Cost": null,
      "ManaCost": null,
      "CoolDown": null,
      "Duration": null
    },
    {
      "Name": "Beastgod Swagger",
      "Class": "Dragoon",
      "ID": null,
      "Description": "For the next 300 seconds, your attacks inflict the Beastgod's curse! (All healing received within 20 seconds is reduced by 50%. Stacks up to 5 times.)",
      "Lore": "Dust Cost: 10 Terra Dust",
      "Level": 5,
      "Type": "Self Blessing",
      "CastTime": "1 second",
      "Vigor Cost": null,
      "ManaCost": 1269,
      "CoolDown": "30 seconds",
      "Duration": null
    },
    {
      "Name": "Tenacious Defender",
      "Class": "Dragoon",
      "ID": null,
      "Description": "Defense increased by (RES*5) for 40 seconds. Also Terra Affinity is increased by 40 for 300 seconds.",
      "Lore": null,
      "Level": 5,
      "Type": "Self Blessing",
      "CastTime": "1 second",
      "Vigor Cost": null,
      "ManaCost": 1844,
      "CoolDown": "300 seconds",
      "Duration": null
    },
    {
      "Name": "Overlord Slaughter",
      "Class": "Dragoon",
      "ID": null,
      "Description": "Chance to Critcast increased when using this skill by 10%. First strike deals and additional 586. Second strike adds (STR*1.0) damage.",
      "Lore": null,
      "Level": 5,
      "Type": "Terra Dual Attack",
      "CastTime": "2 seconds",
      "Vigor Cost": null,
      "ManaCost": 3137,
      "CoolDown": "30 seconds",
      "Duration": null
    },
    {
      "Name": "Violet Scale",
      "Class": "Dragoon",
      "ID": null,
      "Description": "For the next 15 seconds, a powerful dragon comes to your aid at the cost of 40% of your max health. 120% of HP removed is converted to STR and INT!",
      "Lore": null,
      "Level": 5,
      "Type": "Self Blessing",
      "CastTime": "1 second",
      "Vigor Cost": null,
      "ManaCost": 4696,
      "CoolDown": "300 seconds",
      "Duration": null
    },
    {
      "Name": "Wrath Mault",
      "Class": "Dragoon",
      "ID": null,
      "Description": "Deals damage in a fan like array to 15 targets. Deals 100% of attack damage.",
      "Lore": null,
      "Level": 5,
      "Type": "Terra Spell",
      "CastTime": "1 second",
      "Vigor Cost": null,
      "ManaCost": 263,
      "CoolDown": "5 seconds",
      "Duration": null
    },
    {
      "Name": "Phoenix Talon",
      "Class": "Dragoon",
      "ID": null,
      "Description": "Deals 108 damage. Has 60% chance to cause target to suffer additional 24 damage every 2 seconds. Lasts 10 seconds.",
      "Lore": null,
      "Level": 5,
      "Type": "Terra Spell",
      "CastTime": "1 second",
      "Vigor Cost": null,
      "ManaCost": 140,
      "CoolDown": "2 seconds",
      "Duration": null
    },
    {
      "Name": "Ghostwhisper",
      "Class": "Dragoon",
      "ID": null,
      "Description": "Provoke nearby enemies. Cast on yourself to cause nearby monsters to attack you. (Selfcast only)",
      "Lore": null,
      "Level": 5,
      "Type": null,
      "CastTime": "2 seconds",
      "Vigor Cost": null,
      "ManaCost": 400,
      "CoolDown": "5 seconds",
      "Duration": null
    },
    {
      "Name": "Dragonseal",
      "Class": "Dragoon",
      "ID": null,
      "Description": "Has a 80% chance to hit all enemies within a 5 yard radius. Deals damage equal to 30% of enemy's current Health. Caster becomes Numb for 3 seconds.",
      "Lore": "(Don't need to select target)",
      "Level": 5,
      "Type": "Terra Curse",
      "CastTime": "1 second",
      "Vigor Cost": 10,
      "ManaCost": 875,
      "CoolDown": "60 seconds",
      "Duration": null
    },
    {
      "Name": "Void Dragon",
      "Class": "Dragoon",
      "ID": null,
      "Description": "Deals 400 damage. Your next attack within 5 seconds will add 300% of attack power.",
      "Lore": null,
      "Level": 5,
      "Type": "Terra Spell",
      "CastTime": "1 second",
      "Vigor Cost": null,
      "ManaCost": 314,
      "CoolDown": "60 seconds",
      "Duration": null
    },
    {
      "Name": "Annihilate",
      "Class": "Dragoon",
      "ID": null,
      "Description": "First strike deals 786 damage. Second strike deals 50% of normal damage plus 392. Third strike deals 100% of normal damage plus 489.",
      "Lore": "Can only be used with the skill Enrage.",
      "Level": 5,
      "Type": "Terra Spell",
      "CastTime": "3 seconds",
      "Vigor Cost": 30,
      "ManaCost": 1551,
      "CoolDown": "60 seconds",
      "Duration": null
    },
    {
      "Name": "Slaughter Wave",
      "Class": "Dragoon",
      "ID": null,
      "Description": "Removes all of target's status effects. No status effect can be obtained during the following 10 seconds.",
      "Lore": null,
      "Level": 5,
      "Type": "Terra Curse",
      "CastTime": "1 second",
      "Vigor Cost": null,
      "ManaCost": 3756,
      "CoolDown": "60 seconds",
      "Duration": null
    },
    {
      "Name": "Hammer of Tushin",
      "Class": "Shaman",
      "ID": null,
      "Description": "Deals 264 damage.",
      "Lore": null,
      "Level": 30,
      "Type": "Physical",
      "CastTime": "1 seconds",
      "Vigor Cost": null,
      "ManaCost": 101,
      "CoolDown": "0 seconds",
      "Duration": null
    },
    {
      "Name": "Smell of the Flowers",
      "Class": "Shaman",
      "ID": null,
      "Description": "Every 2 seconds 212 Health is rejuvenated. Lasts 7 seconds. Healing effect increases with higher Intellect and skill LV.",
      "Lore": null,
      "Level": 30,
      "Type": null,
      "CastTime": "2 seconds",
      "Vigor Cost": null,
      "ManaCost": 948,
      "CoolDown": "5 seconds",
      "Duration": null
    },
    {
      "Name": "Void Clap",
      "Class": "Shaman",
      "ID": null,
      "Description": "Adds 34 damage.",
      "Lore": null,
      "Level": 5,
      "Type": "Flora Spell",
      "CastTime": "1 second",
      "Vigor Cost": null,
      "ManaCost": 16,
      "CoolDown": "3 seconds",
      "Duration": null
    },
    {
      "Name": "Wise Advice",
      "Class": "Shaman",
      "ID": null,
      "Description": "Adds 10 to Intelligence. Adds 200 to Max Health.",
      "Lore": null,
      "Level": 5,
      "Type": "Passive",
      "CastTime": null,
      "Vigor Cost": null,
      "ManaCost": null,
      "CoolDown": null,
      "Duration": null
    },
    {
      "Name": "Presence of the Spirit",
      "Class": "Shaman",
      "ID": null,
      "Description": "Revives target player with 70% Health. Experience and Spirit loss are reduced by 0.5%.",
      "Lore": null,
      "Level": 5,
      "Type": null,
      "CastTime": "2 seconds",
      "Vigor Cost": null,
      "ManaCost": 1188,
      "CoolDown": "5 minutes",
      "Duration": null
    },
    {
      "Name": "Miasmic Cyclone",
      "Class": "Shaman",
      "ID": null,
      "Description": "Deals 414 damage.",
      "Lore": null,
      "Level": 30,
      "Type": "Flora Spell",
      "CastTime": "1 second",
      "Vigor Cost": null,
      "ManaCost": 419,
      "CoolDown": "2 seconds",
      "Duration": null
    },
    {
      "Name": "Divine Inspiration",
      "Class": "Shaman",
      "ID": null,
      "Description": "Increases Critical hit chances by 10% for 300 seconds.",
      "Lore": null,
      "Level": 5,
      "Type": null,
      "CastTime": "2 seconds",
      "Vigor Cost": null,
      "ManaCost": 276,
      "CoolDown": "5 seconds",
      "Duration": null
    },
    {
      "Name": "Beastial Impulse",
      "Class": "Shaman",
      "ID": null,
      "Description": "When transformed into any Beatskin form, max Health is increased by 30%.",
      "Lore": null,
      "Level": 10,
      "Type": "Passive",
      "CastTime": null,
      "Vigor Cost": null,
      "ManaCost": null,
      "CoolDown": null,
      "Duration": null
    },
    {
      "Name": "Lotus Array",
      "Class": "Shaman",
      "ID": null,
      "Description": "Deals 762 damage.",
      "Lore": null,
      "Level": 10,
      "Type": "Flora Spell",
      "CastTime": "2 seconds",
      "Vigor Cost": null,
      "ManaCost": 419,
      "CoolDown": "3 seconds",
      "Duration": null
    },
    {
      "Name": "Sanguine Rite",
      "Class": "Shaman",
      "ID": null,
      "Description": "Lose 5% of Health every 2 seconds. For the next 10 seconds STR and INT are increased by 400.",
      "Lore": null,
      "Level": 10,
      "Type": null,
      "CastTime": "1 second",
      "Vigor Cost": null,
      "ManaCost": 1029,
      "CoolDown": "60 seconds",
      "Duration": null
    },
    {
      "Name": "Ethereal Infusion",
      "Class": "Shaman",
      "ID": null,
      "Description": "Bless a friendly target. White transformed as Elementa all Elemental Affinities are increased by 30. Lasts 330 seconds.",
      "Lore": null,
      "Level": 10,
      "Type": null,
      "CastTime": "2 seconds",
      "Vigor Cost": null,
      "ManaCost": 1239,
      "CoolDown": "5 seconds",
      "Duration": null
    },
    {
      "Name": "Tushin's Arrogance",
      "Class": "Shaman",
      "ID": null,
      "Description": "Critstrike damage increased by 40%. Critcast damage increased by 40%.",
      "Lore": null,
      "Level": 5,
      "Type": null,
      "CastTime": null,
      "Vigor Cost": null,
      "ManaCost": null,
      "CoolDown": null,
      "Duration": null
    },
    {
      "Name": "Moxi Surrender",
      "Class": "Shaman",
      "ID": null,
      "Description": "Has a 80% chance to lower target's STR and INT for 20 seconds by 80%.",
      "Lore": null,
      "Level": 5,
      "Type": "Flora Curse",
      "CastTime": "1 second",
      "Vigor Cost": null,
      "ManaCost": 1587,
      "CoolDown": "60 seconds",
      "Duration": null
    },
    {
      "Name": "All in a Mouse's Night",
      "Class": "Shaman",
      "ID": null,
      "Description": "Transform into a mouse, with increased speed by 4.0. Absorbs 30% of all damage and dispels all status ailments for 40 seconds. Flora Affinity is increased by 40. Lasts 300 seconds.",
      "Lore": "Dust Cost: 20 Flora Dust",
      "Level": 5,
      "Type": "Self Blessing",
      "CastTime": "1 second",
      "Vigor Cost": null,
      "ManaCost": 2305,
      "CoolDown": "120 seconds",
      "Duration": null
    },
    {
      "Name": "Crime and Punishment",
      "Class": "Shaman",
      "ID": null,
      "Description": "Chance to Critcast increased when using this skill by 10%. First strike adds 569 damage. Second strike adds (Flora*10) damage.",
      "Lore": null,
      "Level": 5,
      "Type": "Flora Dual Attack",
      "CastTime": "2 seconds",
      "Vigor Cost": null,
      "ManaCost": 3922,
      "CoolDown": "30 seconds",
      "Duration": null
    },
    {
      "Name": "Sawn and Lotus",
      "Class": "Shaman",
      "ID": null,
      "Description": "Within a radius of 20 yards, up to 10 allies have all negative status ailments dispelled for 20 seconds.",
      "Lore": null,
      "Level": 5,
      "Type": "Allies Blessing",
      "CastTime": "1 second",
      "Vigor Cost": null,
      "ManaCost": 5872,
      "CoolDown": "120 seconds",
      "Duration": null
    },
    {
      "Name": "Totem Stomp",
      "Class": "Shaman",
      "ID": null,
      "Description": "Up to 15 targets within a 5 yard radius of caster suffer 100% of attack damage.",
      "Lore": null,
      "Level": 5,
      "Type": "Flora Spell",
      "CastTime": "1 second",
      "Vigor Cost": null,
      "ManaCost": 263,
      "CoolDown": "1 second",
      "Duration": null
    },
    {
      "Name": "Essence Aura",
      "Class": "Shaman",
      "ID": null,
      "Description": "All damage taken by target is reduced by 25%. Lasts 15 seconds.",
      "Lore": null,
      "Level": 5,
      "Type": null,
      "CastTime": "2 seconds",
      "Vigor Cost": null,
      "ManaCost": 703,
      "CoolDown": "5 seconds",
      "Duration": null
    },
    {
      "Name": "Metabolic Hat",
      "Class": "Shaman",
      "ID": null,
      "Description": "Target cannot eat for 3 seconds.",
      "Lore": null,
      "Level": 5,
      "Type": "Flora Curse",
      "CastTime": "2 seconds",
      "Vigor Cost": 10,
      "ManaCost": 1094,
      "CoolDown": "150 seconds",
      "Duration": null
    },
    {
      "Name": "Temple of the Soul",
      "Class": "Shaman",
      "ID": null,
      "Description": "Caster gains Invincibility status. All status effects are dispelled and all incoming damage is prevented.",
      "Lore": null,
      "Level": 5,
      "Type": null,
      "CastTime": "1 second",
      "Vigor Cost": null,
      "ManaCost": 785,
      "CoolDown": "300 seconds",
      "Duration": "10 seconds"
    },
    {
      "Name": "Violet Malevolence",
      "Class": "Shaman",
      "ID": null,
      "Description": "Reomves any immunities to Sleep and Stun.",
      "Lore": null,
      "Level": 5,
      "Type": null,
      "CastTime": "2 seconds",
      "Vigor Cost": 30,
      "ManaCost": 971,
      "CoolDown": "30 seconds",
      "Duration": "7 seconds"
    },
    {
      "Name": "Aggressive Edge",
      "Class": "Shaman",
      "ID": null,
      "Description": "Summoned entity draws the attention of up to 10 nearby enemies for 15 seconds.",
      "Lore": "(Effect does not work on Bosses)",
      "Level": 5,
      "Type": null,
      "CastTime": "2 seconds",
      "Vigor Cost": null,
      "ManaCost": 1174,
      "CoolDown": "300 seconds",
      "Duration": null
    },
    {
      "Name": "Kindle Kit",
      "Class": "Conjurer",
      "ID": null,
      "Description": "Deals 294 damage.",
      "Lore": null,
      "Level": 30,
      "Type": "Physical",
      "CastTime": "1 second",
      "Vigor Cost": null,
      "ManaCost": 107,
      "CoolDown": "0 seconds",
      "Duration": null
    },
    {
      "Name": "Snore Stork",
      "Class": "Conjurer",
      "ID": null,
      "Description": "Has a 70% chance to Stupefy target for 16 seconds.",
      "Lore": "Stupefied targets will revert if attacked.",
      "Level": 5,
      "Type": "Pyros Curse",
      "CastTime": "2 seconds",
      "Vigor Cost": null,
      "ManaCost": 582,
      "CoolDown": "30 seconds",
      "Duration": null
    },
    {
      "Name": "Embernado",
      "Class": "Conjurer",
      "ID": null,
      "Description": "Adds 41 damage.",
      "Lore": null,
      "Level": 5,
      "Type": "Pyros Spell",
      "CastTime": "1 second",
      "Vigor Cost": null,
      "ManaCost": 18,
      "CoolDown": "3 seconds",
      "Duration": null
    },
    {
      "Name": "Pheno Barrier",
      "Class": "Conjurer",
      "ID": null,
      "Description": "Absorbs 30% of physical damage. Lasts 10 seconds.",
      "Lore": null,
      "Level": 5,
      "Type": null,
      "CastTime": "1 second",
      "Vigor Cost": null,
      "ManaCost": 149,
      "CoolDown": "60 seconds",
      "Duration": null
    },
    {
      "Name": "Static Spark",
      "Class": "Conjurer",
      "ID": null,
      "Description": "Deals 639 damage",
      "Lore": null,
      "Level": 30,
      "Type": "Aquan Spell",
      "CastTime": "2 seconds",
      "Vigor Cost": null,
      "ManaCost": 88,
      "CoolDown": "3 seconds",
      "Duration": null
    },
    {
      "Name": "Phoenix Flare",
      "Class": "Conjurer",
      "ID": null,
      "Description": "Deals 1002 damage. Has a chance to Ensnare target for 3 seconds.",
      "Lore": null,
      "Level": 30,
      "Type": "Pyros Spell",
      "CastTime": "2 seconds",
      "Vigor Cost": null,
      "ManaCost": 447,
      "CoolDown": "5 seconds",
      "Duration": null
    },
    {
      "Name": "Kylai's Kiss",
      "Class": "Conjurer",
      "ID": null,
      "Description": "Deals 484 damage. Has 40% chance to freeze target in a block of Aquan ice for 3 seconds.",
      "Lore": null,
      "Level": 25,
      "Type": "Aquan Spell",
      "CastTime": "1 second",
      "Vigor Cost": null,
      "ManaCost": 447,
      "CoolDown": "5 seconds",
      "Duration": null
    },
    {
      "Name": "Icy Meditation",
      "Class": "Conjurer",
      "ID": null,
      "Description": "Temporarily freezes self in ice, preventing all actions. Removes negative status effects and prevents damage. Use spell again to cancel the effect!  Ice blocl lasts 10.0 seconds.",
      "Lore": null,
      "Level": 10,
      "Type": null,
      "CastTime": "0.4 seconds",
      "Vigor Cost": null,
      "ManaCost": 713,
      "CoolDown": "300 seconds",
      "Duration": null
    },
    {
      "Name": "Glacial Wrath",
      "Class": "Conjurer",
      "ID": null,
      "Description": "Blast target area with a 15 yard radius. Attacks up to 15 targets with 70% damage. Adds 1002 damage. Target has 60% chance to Freeze.",
      "Lore": null,
      "Level": 10,
      "Type": "Aquan Spell",
      "CastTime": "2 seconds",
      "Vigor Cost": 30,
      "ManaCost": 1791,
      "CoolDown": "60 seconds",
      "Duration": "6 seconds"
    },
    {
      "Name": "Reef Fizz",
      "Class": "Conjurer",
      "ID": null,
      "Description": "Absorbs 50% incoming Aquan damage. Lasts 15 seconds.",
      "Lore": null,
      "Level": 10,
      "Type": null,
      "CastTime": "1 second",
      "Vigor Cost": null,
      "ManaCost": 1097,
      "CoolDown": "60 seconds",
      "Duration": null
    },
    {
      "Name": "Conjure Ethershard",
      "Class": "Conjurer",
      "ID": null,
      "Description": "Conjure one LV 10 Ethershard. Use to add 30 points of INT for 10 minutes.",
      "Lore": "Req Items: 2 Pyros Dust. (Dissolves after use has been offline for 10 minutes)",
      "Level": 10,
      "Type": null,
      "CastTime": "1 second",
      "Vigor Cost": 20,
      "ManaCost": 1321,
      "CoolDown": "5 seconds",
      "Duration": null
    },
    {
      "Name": "Lucky Luck",
      "Class": "Conjurer",
      "ID": null,
      "Description": "INT +500. Resistance increased by 500.",
      "Lore": null,
      "Level": 5,
      "Type": "Passive",
      "CastTime": null,
      "Vigor Cost": null,
      "ManaCost": null,
      "CoolDown": null,
      "Duration": null
    },
    {
      "Name": "Fleece Charm",
      "Class": "Conjurer",
      "ID": null,
      "Description": "Has an 80% chance to cause a 20 second lamb transformation on the target. Cursed targets have their movement speed lowered to 1 and cannot eat, drink, or cast spells!",
      "Lore": "(Reverts to normal if attacked)",
      "Level": 5,
      "Type": "Aquan Curse",
      "CastTime": "1 second",
      "Vigor Cost": null,
      "ManaCost": 3950,
      "CoolDown": "60 seconds",
      "Duration": null
    },
    {
      "Name": "Eternal Law",
      "Class": "Conjurer",
      "ID": null,
      "Description": "Resistance increased by (INT*1.0). Critcast chance increased by 20%. Lasts 40 seconds.",
      "Lore": null,
      "Level": 5,
      "Type": "Self Blessing",
      "CastTime": "1 second",
      "Vigor Cost": null,
      "ManaCost": 2460,
      "CoolDown": "120 seconds",
      "Duration": null
    },
    {
      "Name": "Double Dragon Smash",
      "Class": "Conjurer",
      "ID": null,
      "Description": "When using this skill, Critcast chance increased by 10%. First strike adds 666 damage. Second strike adds (Pyr Aff*10) damage.",
      "Lore": null,
      "Level": 5,
      "Type": "Aquan Dual Attack",
      "CastTime": "2 seconds",
      "Vigor Cost": null,
      "ManaCost": 4184,
      "CoolDown": "30 seconds",
      "Duration": null
    },
    {
      "Name": "Phoenix and Lotus",
      "Class": "Conjurer",
      "ID": null,
      "Description": "For 600 seconds Pyros Affinity is increased by 80 and 50% of fire damage is absorbed.",
      "Lore": null,
      "Level": 5,
      "Type": "Self Blessing",
      "CastTime": "1 second",
      "Vigor Cost": null,
      "ManaCost": 3128,
      "CoolDown": "30 seconds",
      "Duration": null
    },
    {
      "Name": "Shiver Gust",
      "Class": "Conjurer",
      "ID": null,
      "Description": "Up to 15 foes within a 5 yard radius of the target suffer 100% of attack damage.",
      "Lore": null,
      "Level": 5,
      "Type": "Aquan Spell",
      "CastTime": "1 second",
      "Vigor Cost": null,
      "ManaCost": 263,
      "CoolDown": "1 second",
      "Duration": null
    },
    {
      "Name": "Ethereal Embrace",
      "Class": "Conjurer",
      "ID": null,
      "Description": "Evokes an Ethershell with a 50% chance to absorb incoming damage by using mana. Lasts 15 seconds.",
      "Lore": null,
      "Level": 5,
      "Type": null,
      "CastTime": "2 seconds",
      "Vigor Cost": null,
      "ManaCost": 751,
      "CoolDown": "30 seconds",
      "Duration": null
    },
    {
      "Name": "Day of Reckoning",
      "Class": "Conjurer",
      "ID": null,
      "Description": "Hits enemies within a radius of 10 yards from target. Hits up to 10 enemies. Deals 866 damage.",
      "Lore": null,
      "Level": 5,
      "Type": "Pyros Spell",
      "CastTime": "2.5 seconds",
      "Vigor Cost": 10,
      "ManaCost": 1166,
      "CoolDown": "60 seconds",
      "Duration": null
    },
    {
      "Name": "Primordial Shell",
      "Class": "Conjurer",
      "ID": null,
      "Description": "Increases Magic Resistance by 50%. Lasts 180 seconds.",
      "Lore": null,
      "Level": 5,
      "Type": null,
      "CastTime": "1 second",
      "Vigor Cost": null,
      "ManaCost": 838,
      "CoolDown": "60 seconds",
      "Duration": null
    },
    {
      "Name": "Scalen Gush",
      "Class": "Conjurer",
      "ID": null,
      "Description": "Hits targets in a 10 yard radius from the caster. Attack up to 10 targets for 70% of normal damage, plus an additional 1158 damage.",
      "Lore": null,
      "Level": 5,
      "Type": "Pyros Spell",
      "CastTime": "2 seconds",
      "Vigor Cost": 30,
      "ManaCost": 2069,
      "CoolDown": "60 seconds",
      "Duration": null
    },
    {
      "Name": "Invoke the Spirit",
      "Class": "Conjurer",
      "ID": null,
      "Description": "Increase target's INT by 40. Lasts 600 seconds.",
      "Lore": null,
      "Level": 5,
      "Type": null,
      "CastTime": "2 seconds",
      "Vigor Cost": null,
      "ManaCost": 1252,
      "CoolDown": "5 seconds",
      "Duration": null
    },
    {
      "Name": "Aurmaan Roar",
      "Class": "Mystic",
      "ID": null,
      "Description": "Deals 280 damage. Has a chance to knock target back 2 yards.",
      "Lore": null,
      "Level": 30,
      "Type": "Physical",
      "CastTime": "1 second",
      "Vigor Cost": null,
      "ManaCost": 107,
      "CoolDown": "0 seconds",
      "Duration": null
    },
    {
      "Name": "Orchid Shower",
      "Class": "Mystic",
      "ID": null,
      "Description": "Instantly heal target for 569. Effect of healing depends on INT and skill LV.",
      "Lore": null,
      "Level": 30,
      "Type": null,
      "CastTime": "2 seconds",
      "Vigor Cost": null,
      "ManaCost": 330,
      "CoolDown": "1 seconds",
      "Duration": null
    },
    {
      "Name": "Midnight Mist",
      "Class": "Mystic",
      "ID": null,
      "Description": "Adds 34 damage.",
      "Lore": null,
      "Level": 5,
      "Type": "Aquan Spell",
      "CastTime": "1 second",
      "Vigor Cost": null,
      "ManaCost": 18,
      "CoolDown": "3 seconds",
      "Duration": null
    },
    {
      "Name": "Path of Righteous",
      "Class": "Mystic",
      "ID": null,
      "Description": "Adds 10 Defense. Adds 200 to Max Health.",
      "Lore": null,
      "Level": 5,
      "Type": "Passive",
      "CastTime": null,
      "Vigor Cost": null,
      "ManaCost": null,
      "CoolDown": null,
      "Duration": null
    },
    {
      "Name": "Arise!",
      "Class": "Mystic",
      "ID": null,
      "Description": "Revives fallen ally healing 10% of Max Health. Experience and Spirit loss is decreased to 0.5%.",
      "Lore": null,
      "Level": 5,
      "Type": null,
      "CastTime": "2 seconds",
      "Vigor Cost": null,
      "ManaCost": 879,
      "CoolDown": "20 seconds",
      "Duration": null
    },
    {
      "Name": "Jinglu Ice",
      "Class": "Mystic",
      "ID": null,
      "Description": "Deals 735 damage. Has a chance to slow by 2 for 3 seconds.",
      "Lore": null,
      "Level": 30,
      "Type": "Aquan Spell",
      "CastTime": "2 seconds",
      "Vigor Cost": null,
      "ManaCost": 447,
      "CoolDown": "2 seconds",
      "Duration": null
    },
    {
      "Name": "Sujilu's Blessing",
      "Class": "Mystic",
      "ID": null,
      "Description": "Grant yourself 30 to Aquan affinity for 600 seconds.",
      "Lore": null,
      "Level": 5,
      "Type": null,
      "CastTime": "2 seconds",
      "Vigor Cost": null,
      "ManaCost": 294,
      "CoolDown": "5 seconds",
      "Duration": null
    },
    {
      "Name": "Seaspray Shell Barrier",
      "Class": "Mystic",
      "ID": null,
      "Description": "Affects nearby allies within a radius of 30 yards. Up to 10 allies have their Defense and Resistance increased by 100% and are immune to Sleep. Lasts 10 seconds.",
      "Lore": null,
      "Level": 10,
      "Type": null,
      "CastTime": "2 seconds",
      "Vigor Cost": 30,
      "ManaCost": 713,
      "CoolDown": "60 seconds",
      "Duration": null
    },
    {
      "Name": "Essence Sap",
      "Class": "Mystic",
      "ID": null,
      "Description": "Reduce target's Essence by 700. Has a 80% chance to succeed.",
      "Lore": null,
      "Level": 10,
      "Type": "Aquan Curse",
      "CastTime": "1 second",
      "Vigor Cost": 30,
      "ManaCost": 895,
      "CoolDown": "30 seconds",
      "Duration": null
    },
    {
      "Name": "Mana Well Quaff",
      "Class": "Mystic",
      "ID": null,
      "Description": "For the next 30 seconds any healing received by allies within a 10 yard radius is increased by 50%.",
      "Lore": null,
      "Level": 10,
      "Type": null,
      "CastTime": "2 seconds",
      "Vigor Cost": null,
      "ManaCost": 1097,
      "CoolDown": "60 seconds",
      "Duration": null
    },
    {
      "Name": "Yehayu Incantation",
      "Class": "Mystic",
      "ID": null,
      "Description": "Removes target's status effects and for the next 26 seconds any healing received from spells is reduced by 95%.",
      "Lore": null,
      "Level": 10,
      "Type": "Aquan Curse",
      "CastTime": "1 second",
      "Vigor Cost": null,
      "ManaCost": 1321,
      "CoolDown": "60 seconds",
      "Duration": null
    },
    {
      "Name": "Infinite Rays",
      "Class": "Mystic",
      "ID": null,
      "Description": "Increase Accuracy by 10. Attack range increased by 1.0 yards.",
      "Lore": null,
      "Level": 5,
      "Type": "Passive",
      "CastTime": null,
      "Vigor Cost": null,
      "ManaCost": null,
      "CoolDown": null,
      "Duration": null
    },
    {
      "Name": "Tale of Tajaka",
      "Class": "Mystic",
      "ID": null,
      "Description": "Conjure a Stone of Principle. May be used to resurrect target fallen ally! When the Stone is upgraded, resurrected allies will lose less EXP and Spirit!",
      "Lore": "Dust Cost: 99 Aquan Dust",
      "Level": 5,
      "Type": "Self Blessing",
      "CastTime": "1 second",
      "Vigor Cost": null,
      "ManaCost": 7111,
      "CoolDown": "5 seconds",
      "Duration": null
    },
    {
      "Name": "Suppression",
      "Class": "Mystic",
      "ID": null,
      "Description": "Has an 80% chance to reduce target's attack range by 80%. Lasts 40 seconds.",
      "Lore": null,
      "Level": 5,
      "Type": "Aquan Curse",
      "CastTime": "1 second",
      "Vigor Cost": null,
      "ManaCost": 4184,
      "CoolDown": "60 seconds",
      "Duration": null
    },
    {
      "Name": "Forceful Dragon",
      "Class": "Mystic",
      "ID": null,
      "Description": "When using this skill, Critcast chance increassed by 10%. First strike adds 553 damage. Second strike adds (DEF*5) damage.",
      "Lore": null,
      "Level": 5,
      "Type": "Aquan Dual Attack",
      "CastTime": "2 seconds",
      "Vigor Cost": null,
      "ManaCost": 4184,
      "CoolDown": "30 seconds",
      "Duration": null
    },
    {
      "Name": "Moban Enlightenment",
      "Class": "Mystic",
      "ID": null,
      "Description": "Effects those within a range of 10 yard radius of caster. Dispel up to 10 allies' healing reduction curses and make them immune to such curses. Effected allies absorb up to 50% of other damage sources and 200% of that damage heals instead. Lasts 40 seconds.",
      "Lore": null,
      "Level": 5,
      "Type": "AOE Blessing",
      "CastTime": "1 second",
      "Vigor Cost": null,
      "ManaCost": 4176,
      "CoolDown": "300 seconds",
      "Duration": null
    },
    {
      "Name": "Lotus Typhoon",
      "Class": "Mystic",
      "ID": null,
      "Description": "Affects enemies within a 5 yard radius. Up to 15 targets suffer 100% of attack damage.",
      "Lore": null,
      "Level": 5,
      "Type": "Aquan Spell",
      "CastTime": "1 second",
      "Vigor Cost": null,
      "ManaCost": 263,
      "CoolDown": "1 second",
      "Duration": null
    },
    {
      "Name": "Auspicious Hymn",
      "Class": "Mystic",
      "ID": null,
      "Description": "Raise target's Max Health by 90% for 300 seconds.",
      "Lore": null,
      "Level": 5,
      "Type": null,
      "CastTime": "2 seconds",
      "Vigor Cost": null,
      "ManaCost": 751,
      "CoolDown": "5 seconds",
      "Duration": null
    },
    {
      "Name": "Manjusha Vex",
      "Class": "Mystic",
      "ID": null,
      "Description": "Affects nearby foes within a radius of 9 yards. Up to 10 foes within have a 80% chance to be Slowed for 6 seconds.",
      "Lore": null,
      "Level": 5,
      "Type": "Aquan Curse",
      "CastTime": "2 seconds",
      "Vigor Cost": 10,
      "ManaCost": 1166,
      "CoolDown": "60 seconds",
      "Duration": null
    },
    {
      "Name": "Divine Radiance",
      "Class": "Mystic",
      "ID": null,
      "Description": "Affects nearby allies within a radius of 30 yards. Up to 10 allies have 30% of their Max Health replenished.",
      "Lore": null,
      "Level": 5,
      "Type": "Group Heal",
      "CastTime": "1 second",
      "Vigor Cost": null,
      "ManaCost": 838,
      "CoolDown": "2 seconds",
      "Duration": null
    },
    {
      "Name": "Warmonk's Hymn",
      "Class": "Mystic",
      "ID": null,
      "Description": "Affects neaby allies within a radius of 10 yards. Up to 10 allies have their Critical hit rates increased by 5% and their Critical damage bonus increased by 25%. Lasts 10 seconds.",
      "Lore": null,
      "Level": 5,
      "Type": null,
      "CastTime": "1 second",
      "Vigor Cost": 30,
      "ManaCost": 553,
      "CoolDown": "60 seconds",
      "Duration": null
    },
    {
      "Name": "Ethershroud",
      "Class": "Mystic",
      "ID": null,
      "Description": "Absorbs 50% of all incoming damage. Will abrosb a total amount of 10000 damage per minute. Lasts for 30 seconds.",
      "Lore": null,
      "Level": 5,
      "Type": null,
      "CastTime": "1 second",
      "Vigor Cost": null,
      "ManaCost": 1252,
      "CoolDown": "10 minutes",
      "Duration": null
    },
    {
      "Name": "Ten Steps Kill",
      "Class": "Blademaster",
      "ID": null,
      "Description": "Has a 90% chance to increase own Critstrike rate by 1% upon each successful Dark Eclipse or Lethal Fangs hit. Can stack up 5 times.",
      "Lore": null,
      "Level": 6,
      "Type": "Aura",
      "CastTime": "10 seconds",
      "Vigor Cost": null,
      "ManaCost": 4500,
      "CoolDown": "300 seconds",
      "Duration": null
    },
    {
      "Name": "Dragon Viper",
      "Class": "Blademaster",
      "ID": null,
      "Description": "Enhance the Viper with Dragon power. Increases the duration time of the '+Critstrike Rate' effect of Ten Steps Kill by 12 seconds.",
      "Lore": null,
      "Level": 6,
      "Type": "Aura",
      "CastTime": null,
      "Vigor Cost": null,
      "ManaCost": null,
      "CoolDown": null,
      "Duration": null
    },
    {
      "Name": "Dark Eclipse",
      "Class": "Blademaster",
      "ID": null,
      "Description": "Damage Addition: 120%. Adds 648 damage to a successful hit.",
      "Lore": "Deals extra 30% INT damage to a poisoned target.",
      "Level": 6,
      "Type": "Ferus Spell",
      "CastTime": "1 second",
      "Vigor Cost": null,
      "ManaCost": 397,
      "CoolDown": "0 seconds",
      "Duration": null
    },
    {
      "Name": "Enriched Poison",
      "Class": "Blademaster",
      "ID": null,
      "Description": "Strike the target with enriched poison. Increeases the additional damage of Dark Eclipse by 30%.",
      "Lore": null,
      "Level": 6,
      "Type": "Aura",
      "CastTime": null,
      "Vigor Cost": null,
      "ManaCost": null,
      "CoolDown": null,
      "Duration": null
    },
    {
      "Name": "Lethal Fangs",
      "Class": "Blademaster",
      "ID": null,
      "Description": "Damage Addition: 200%. Adds 1114 damage to a successful hit.",
      "Lore": "A powerful AOE attack. Has a high chance to poison targets.",
      "Level": 6,
      "Type": "Ferus Spell",
      "CastTime": "2 seconds",
      "Vigor Cost": null,
      "ManaCost": 961,
      "CoolDown": "5 seconds",
      "Duration": null
    },
    {
      "Name": "Condensed Venom",
      "Class": "Blademaster",
      "ID": null,
      "Description": "Strike the target with condensed venom. Increases the additional damage of Lethal Fangs by 30%.",
      "Lore": null,
      "Level": 6,
      "Type": "Aura",
      "CastTime": null,
      "Vigor Cost": null,
      "ManaCost": null,
      "CoolDown": null,
      "Duration": null
    },
    {
      "Name": "Sinister Curse",
      "Class": "Blademaster",
      "ID": null,
      "Description": "Reduces the target's Defense and Resistance by 2500. Reduces target's Ferus Resistance by 50 for 35 seconds.",
      "Lore": null,
      "Level": 5,
      "Type": "Instant Curse",
      "CastTime": "1 second",
      "Vigor Cost": null,
      "ManaCost": 512,
      "CoolDown": "30 seconds",
      "Duration": null
    },
    {
      "Name": "Crippling Assault",
      "Class": "Blademaster",
      "ID": null,
      "Description": "Deals 90% of INT in damage initially. Targets bleeds for an additional 270% INT damage. Bleeding ignores defense. This effect can be stacked up to 5 times.",
      "Lore": null,
      "Level": 5,
      "Type": "Ferus Spell",
      "CastTime": "1 second",
      "Vigor Cost": null,
      "ManaCost": 535,
      "CoolDown": "2 seconds",
      "Duration": null
    },
    {
      "Name": "Million Miles",
      "Class": "Assassin",
      "ID": null,
      "Description": "Recovers Vigor by 6 per 5 seconds.",
      "Lore": null,
      "Level": 6,
      "Type": "Aura",
      "CastTime": "10 seconds",
      "Vigor Cost": null,
      "ManaCost": 4500,
      "CoolDown": "300 seconds",
      "Duration": null
    },
    {
      "Name": "Star of Jade",
      "Class": "Assassin",
      "ID": null,
      "Description": "Summons the Star Jade. Increases the Vigor recovery effect of Million Miles by 6 per 5 seconds.",
      "Lore": null,
      "Level": 6,
      "Type": "Aura",
      "CastTime": null,
      "Vigor Cost": null,
      "ManaCost": null,
      "CoolDown": null,
      "Duration": null
    },
    {
      "Name": "Lunar Glow",
      "Class": "Assassin",
      "ID": null,
      "Description": "Damage Addition: 180.0%. Adds 973 damage upon a successful hit.",
      "Lore": "Only available in stealth mobde. Silences target for 3 seconds.",
      "Level": 6,
      "Type": "Ferus Spell",
      "CastTime": "1 second",
      "Vigor Cost": null,
      "ManaCost": 397,
      "CoolDown": "0 seconds",
      "Duration": null
    },
    {
      "Name": "Thunder Charge",
      "Class": "Assassin",
      "ID": null,
      "Description": "Increases the critcast rate of Lunar Glow by 30%.",
      "Lore": null,
      "Level": 6,
      "Type": "Aura",
      "CastTime": null,
      "Vigor Cost": null,
      "ManaCost": null,
      "CoolDown": null,
      "Duration": null
    },
    {
      "Name": "Muscle Shear",
      "Class": "Assassin",
      "ID": null,
      "Description": "Shear the key muscles of the target. Paralyzes target for 20 seconds at a 83% successful rate. Available in Stealth mode.",
      "Lore": null,
      "Level": 6,
      "Type": "Ferus Curse",
      "CastTime": "1 second",
      "Vigor Cost": null,
      "ManaCost": 397,
      "CoolDown": "10 seconds",
      "Duration": null
    },
    {
      "Name": "Denied Negative",
      "Class": "Assassin",
      "ID": null,
      "Description": "Increases the successful rate of Muscle Shear by 18% duration time by 12 seconds.",
      "Lore": null,
      "Level": 6,
      "Type": "Aura",
      "CastTime": null,
      "Vigor Cost": null,
      "ManaCost": null,
      "CoolDown": null,
      "Duration": null
    },
    {
      "Name": "Silent Killing",
      "Class": "Assassin",
      "ID": null,
      "Description": "Silences the target for 8 seconds and bleeds for 85% of the casters INT in damage every second silence is in effect. Bleeding ignores defense.",
      "Lore": null,
      "Level": 5,
      "Type": "Ferus Curse",
      "CastTime": "1 second",
      "Vigor Cost": null,
      "ManaCost": 512,
      "CoolDown": "25 seconds",
      "Duration": null
    },
    {
      "Name": "Dense Aura",
      "Class": "Assassin",
      "ID": null,
      "Description": "Smog will surround you for 25 seconds. All targets near you will be influenced by Dense Aura. Reduces the target's Accuracy by 75 and Movement Speed by 5 m/s.",
      "Lore": null,
      "Level": 5,
      "Type": "Group Curse",
      "CastTime": "0 seconds",
      "Vigor Cost": null,
      "ManaCost": 535,
      "CoolDown": "120 seconds.",
      "Duration": null
    },
    {
      "Name": "Prayers of Nature",
      "Class": "Marksman",
      "ID": null,
      "Description": "Increases Affinities by 10. Increases mounted and barefoot speed by 0.6y/s.",
      "Lore": null,
      "Level": 6,
      "Type": "Aura",
      "CastTime": "10 seconds",
      "Vigor Cost": null,
      "ManaCost": 4500,
      "CoolDown": "300 seconds",
      "Duration": null
    },
    {
      "Name": "Worshipper of Nature",
      "Class": "Marksman",
      "ID": null,
      "Description": "Prayers of Nature increases 12 more Affinities. It also increases 0.6y/s more mounted and barefoot speed.",
      "Lore": null,
      "Level": 6,
      "Type": "Aura",
      "CastTime": null,
      "Vigor Cost": null,
      "ManaCost": null,
      "CoolDown": null,
      "Duration": null
    },
    {
      "Name": "Breath of Nature",
      "Class": "Marksman",
      "ID": null,
      "Description": "Damage Addition: 120.0%. Adds 626 damage upon a successful hit.",
      "Lore": "Increases own Accuracy by 12.",
      "Level": 6,
      "Type": "Flora Spell",
      "CastTime": "1 second",
      "Vigor Cost": null,
      "ManaCost": 460,
      "CoolDown": "3 seconds",
      "Duration": null
    },
    {
      "Name": "Driller Tusk",
      "Class": "Marksman",
      "ID": null,
      "Description": "Increases the additional damage of Breath of Nature by 24%.",
      "Lore": null,
      "Level": 6,
      "Type": "Aura",
      "CastTime": null,
      "Vigor Cost": null,
      "ManaCost": null,
      "CoolDown": null,
      "Duration": null
    },
    {
      "Name": "Arrow Downpour",
      "Class": "Marksman",
      "ID": null,
      "Description": "Damage Addition: 137%. Adds damage: 1076.",
      "Lore": "Does Damage and slow target by 1.6 y/s.",
      "Level": 6,
      "Type": "Aquan Spell",
      "CastTime": "2 seconds",
      "Vigor Cost": null,
      "ManaCost": 1105,
      "CoolDown": "15 seconds",
      "Duration": null
    },
    {
      "Name": "Sharpened Ego",
      "Class": "Marksman",
      "ID": null,
      "Description": "Increases the additional damage of Arrow Downpour by 24%.",
      "Lore": null,
      "Level": 6,
      "Type": "Aura",
      "CastTime": null,
      "Vigor Cost": null,
      "ManaCost": null,
      "CoolDown": null,
      "Duration": null
    },
    {
      "Name": "Arrow Reflection",
      "Class": "Marksman",
      "ID": null,
      "Description": "Causes the target to suffer from bleeding. Deals 360% INT damage over 21 seconds. This effect can be stacked up to 5 times.",
      "Lore": null,
      "Level": 5,
      "Type": "Flora Spell",
      "CastTime": "2 seconds",
      "Vigor Cost": null,
      "ManaCost": 512,
      "CoolDown": "3 seconds",
      "Duration": null
    },
    {
      "Name": "Fatal Arrow",
      "Class": "Marksman",
      "ID": null,
      "Description": "Deals 160% INT damage. Each Arrow Reflection inflicted on the target will increase this effect by 40%. This damage is unaffected by Elemental Points or Elemental Resistance.",
      "Lore": null,
      "Level": 5,
      "Type": "Flora Spell",
      "CastTime": "1 second",
      "Vigor Cost": null,
      "ManaCost": 535,
      "CoolDown": "8 seconds",
      "Duration": null
    },
    {
      "Name": "Ether Strider",
      "Class": "Seeker",
      "ID": null,
      "Description": "Increases flying speed by 1.2 m/s. Increases Vigor recovery by 6.",
      "Lore": null,
      "Level": 6,
      "Type": "Aura",
      "CastTime": "10 seconds",
      "Vigor Cost": null,
      "ManaCost": 4500,
      "CoolDown": "300 seconds",
      "Duration": null
    },
    {
      "Name": "Soul Burst",
      "Class": "Seeker",
      "ID": null,
      "Description": "Ether Strider receives an additional increase in flying speed by 1.2 m/s, Additional increase to Vigor recovery rate by 6.",
      "Lore": null,
      "Level": 6,
      "Type": "Aura",
      "CastTime": null,
      "Vigor Cost": null,
      "ManaCost": null,
      "CoolDown": null,
      "Duration": null
    },
    {
      "Name": "Flowing Clouds",
      "Class": "Seeker",
      "ID": null,
      "Description": "Increases Terra and Ferus resistances by 60.",
      "Lore": null,
      "Level": 6,
      "Type": "Self-Blessing",
      "CastTime": "1 second",
      "Vigor Cost": null,
      "ManaCost": 1105,
      "CoolDown": "120 seconds",
      "Duration": "14 seconds"
    },
    {
      "Name": "Gale Turbulence",
      "Class": "Seeker",
      "ID": null,
      "Description": "Flowing Clouds grants 60 more Terra and Ferus resistance points.",
      "Lore": null,
      "Level": 6,
      "Type": "Aura",
      "CastTime": null,
      "Vigor Cost": null,
      "ManaCost": null,
      "CoolDown": null,
      "Duration": null
    },
    {
      "Name": "Arrow Storm",
      "Class": "Seeker",
      "ID": null,
      "Description": "Damage Addition: 137%. Adds 1076 damage upon a successful hit.",
      "Lore": "Damages several targets in front of you and grounds flying targets for 12 seconds.",
      "Level": 6,
      "Type": "Flora Spell",
      "CastTime": "3 seconds",
      "Vigor Cost": null,
      "ManaCost": 1105,
      "CoolDown": "300 seconds",
      "Duration": null
    },
    {
      "Name": "Menacing Cloud",
      "Class": "Seeker",
      "ID": null,
      "Description": "Increases the ban fly time of Arrow Storm by 6 seconds.",
      "Lore": null,
      "Level": 6,
      "Type": "Aura",
      "CastTime": null,
      "Vigor Cost": null,
      "ManaCost": null,
      "CoolDown": null,
      "Duration": null
    },
    {
      "Name": "Lofty Ambition",
      "Class": "Seeker",
      "ID": null,
      "Description": "Removes all negative effects and grants immunity to Immobilize and Slow effects for 5 seconds. During this time, the Seeker can recover HP and MP by 35% per second. Usable while under the Silence and Stun effects.",
      "Lore": null,
      "Level": 5,
      "Type": "Self-Blessing",
      "CastTime": "1 second",
      "Vigor Cost": null,
      "ManaCost": 512,
      "CoolDown": "100 seconds",
      "Duration": null
    },
    {
      "Name": "Ether Arrow",
      "Class": "Seeker",
      "ID": null,
      "Description": "Deals 115% spell damage. The target suffers 3895 Mana and 395 Vigor reduction every second for 5 seconds.",
      "Lore": null,
      "Level": 5,
      "Type": "Flora Spell",
      "CastTime": "2 seconds",
      "Vigor Cost": null,
      "ManaCost": 535,
      "CoolDown": "12 seconds",
      "Duration": null
    },
    {
      "Name": "Mountain Fortitude",
      "Class": "Guardian",
      "ID": null,
      "Description": "Reduces own INT by 63%. Increases own Defense and Resistances by 40%. Reduces physical damage taken by 40%. Increases Max HP by 3000.",
      "Lore": null,
      "Level": 6,
      "Type": "Aura",
      "CastTime": "10 seconds",
      "Vigor Cost": null,
      "ManaCost": 4500,
      "CoolDown": "300 seconds",
      "Duration": null
    },
    {
      "Name": "Demon Star",
      "Class": "Guardian",
      "ID": null,
      "Description": "Mountain Fortitude reduces 18% less INT and increases 30% more Defense and Resistance. Increases Physical damage evasion by 30%. Increases max HP by 1500.",
      "Lore": null,
      "Level": 6,
      "Type": "Aura",
      "CastTime": null,
      "Vigor Cost": null,
      "ManaCost": null,
      "CoolDown": null,
      "Duration": null
    },
    {
      "Name": "Wave Lunge",
      "Class": "Guardian",
      "ID": null,
      "Description": "Damage Addition: 120.0%. Adds 574 damage upon a successful hit.",
      "Lore": "Attack the targets with great taunt effect. Each successful hit will reduce own damage taken by 1% for 30 seconds. Can stack up to 5 times.",
      "Level": 6,
      "Type": "Terra Damage",
      "CastTime": "1 second",
      "Vigor Cost": null,
      "ManaCost": 369,
      "CoolDown": "1 second",
      "Duration": null
    },
    {
      "Name": "Ghost Star",
      "Class": "Guardian",
      "ID": null,
      "Description": "Adds a special effect to Wave Lunge. Makes it have a 90% chance to reduce damage taken by 6%.",
      "Lore": null,
      "Level": 6,
      "Type": "Aura",
      "CastTime": null,
      "Vigor Cost": null,
      "ManaCost": null,
      "CoolDown": null,
      "Duration": null
    },
    {
      "Name": "Smell of Slaughter",
      "Class": "Guardian",
      "ID": null,
      "Description": "Taunt nearby monsters.",
      "Lore": null,
      "Level": 6,
      "Type": "Terra Spell",
      "CastTime": "1 second",
      "Vigor Cost": null,
      "ManaCost": 413,
      "CoolDown": "30 seconds",
      "Duration": "17 seconds"
    },
    {
      "Name": "Sacrificing Star",
      "Class": "Guardian",
      "ID": null,
      "Description": "Reduces the cooldown time of Smell of Slaughter by 18 seconds. After a successful Smell of Slaughter cast, damage taken for the next 18 seconds is reduced by 12%.",
      "Lore": null,
      "Level": 6,
      "Type": "Aura",
      "CastTime": null,
      "Vigor Cost": null,
      "ManaCost": null,
      "CoolDown": null,
      "Duration": null
    },
    {
      "Name": "Transient Aegis",
      "Class": "Guardian",
      "ID": null,
      "Description": "Reduces 70% Physical damage to yourself. This effect will last for 30 seconds or until the target is attacked 5 times.",
      "Lore": null,
      "Level": 5,
      "Type": "Self-Blessing",
      "CastTime": null,
      "Vigor Cost": null,
      "ManaCost": 535,
      "CoolDown": "30 seconds",
      "Duration": null
    },
    {
      "Name": "Self Force",
      "Class": "Guardian",
      "ID": null,
      "Description": "Temporarily increases Max HP by 35%. Also recovers 35% HP. Lasts 15 seconds.",
      "Lore": null,
      "Level": 5,
      "Type": "Self-Blessing",
      "CastTime": null,
      "Vigor Cost": null,
      "ManaCost": 535,
      "CoolDown": "120 seconds",
      "Duration": null
    },
    {
      "Name": "God of Duel",
      "Class": "Vanguard",
      "ID": null,
      "Description": "Reduces own Defense by 24% and transfer it to INT. Increases Critcast damage by 12%.",
      "Lore": null,
      "Level": 6,
      "Type": "Aura",
      "CastTime": "10 seconds",
      "Vigor Cost": null,
      "ManaCost": 4500,
      "CoolDown": "300 seconds",
      "Duration": null
    },
    {
      "Name": "Valor Star",
      "Class": "Vanguard",
      "ID": null,
      "Description": "Makes God of Duel increases 6% more INT and reduces 12% more Defense. Increases Critcast damage by 12%.",
      "Lore": null,
      "Level": 6,
      "Type": "Aura",
      "CastTime": null,
      "Vigor Cost": null,
      "ManaCost": null,
      "CoolDown": null,
      "Duration": null
    },
    {
      "Name": "Evil Buster",
      "Class": "Vanguard",
      "ID": null,
      "Description": "Damage Addition: 120.0%. Adds 574 damage upon a successful hit.",
      "Lore": "Deals a damage while slow target by 1.8 y/s.",
      "Level": 6,
      "Type": "Terra Damage",
      "CastTime": "1 second",
      "Vigor Cost": null,
      "ManaCost": 734,
      "CoolDown": "6 seconds",
      "Duration": null
    },
    {
      "Name": "Mercy Star",
      "Class": "Vanguard",
      "ID": null,
      "Description": "Increases the deceleration effect of Evil Buster by 1.8 m/s.",
      "Lore": null,
      "Level": 6,
      "Type": "Aura",
      "CastTime": null,
      "Vigor Cost": null,
      "ManaCost": null,
      "CoolDown": null,
      "Duration": null
    },
    {
      "Name": "Suicide Assault",
      "Class": "Vanguard",
      "ID": null,
      "Description": "Damage Addition: 120.0%. Adds 574 damage upon a successful hit.",
      "Lore": "Greatly reduces Essence of target if it has been hit by Evil Buster.",
      "Level": 6,
      "Type": "Terra Damage",
      "CastTime": "1 second",
      "Vigor Cost": null,
      "ManaCost": 413,
      "CoolDown": "3 seconds",
      "Duration": null
    },
    {
      "Name": "Faith Star",
      "Class": "Vanguard",
      "ID": null,
      "Description": "Makes Suicide Assault reduces 30% more Essence. Increases the additional damage by 60%.",
      "Lore": null,
      "Level": 6,
      "Type": "Aura",
      "CastTime": null,
      "Vigor Cost": null,
      "ManaCost": null,
      "CoolDown": null,
      "Duration": null
    },
    {
      "Name": "Mirror Defense",
      "Class": "Vanguard",
      "ID": null,
      "Description": "Reflects the target's Mana attack with a Mirror Defense. Causes the attacker to take 70% of their own damage. This effect will last for 30 seconds or until the target is attacked 5 times.",
      "Lore": null,
      "Level": 5,
      "Type": "Self-Blessing",
      "CastTime": null,
      "Vigor Cost": null,
      "ManaCost": 535,
      "CoolDown": "120 seconds",
      "Duration": null
    },
    {
      "Name": "Fatal Spear",
      "Class": "Vanguard",
      "ID": null,
      "Description": "A ranged spear attack. Deals 200% Terra damage. The target will be stunned for 7 seconds if it has been hit by Evil Buster.",
      "Lore": null,
      "Level": 5,
      "Type": "Terra Spell",
      "CastTime": null,
      "Vigor Cost": null,
      "ManaCost": 512,
      "CoolDown": "8 seconds",
      "Duration": null
    },
    {
      "Name": "Fountain of the Sky",
      "Class": "Templar",
      "ID": null,
      "Description": "Increases the Elemental Resistance of all friendly units within 30 yards by 18.",
      "Lore": null,
      "Level": 6,
      "Type": "Fountain of Sky",
      "CastTime": "10 seconds",
      "Vigor Cost": null,
      "ManaCost": 4500,
      "CoolDown": "300 seconds",
      "Duration": null
    },
    {
      "Name": "Rocky Fortify",
      "Class": "Templar",
      "ID": null,
      "Description": "Fountain Sky increases 12 more own Ferus Resistance.",
      "Lore": null,
      "Level": 6,
      "Type": "Aura",
      "CastTime": null,
      "Vigor Cost": null,
      "ManaCost": null,
      "CoolDown": null,
      "Duration": null
    },
    {
      "Name": "Universal Judgement",
      "Class": "Templar",
      "ID": null,
      "Description": "Protects all friendly units within a range. In 13 seconds, reduces damage taking by 32%.",
      "Lore": null,
      "Level": 6,
      "Type": "Massive Blessing",
      "CastTime": "2 seconds",
      "Vigor Cost": null,
      "ManaCost": 2923,
      "CoolDown": "300 seconds",
      "Duration": null
    },
    {
      "Name": "Wolfero Fortify",
      "Class": "Templar",
      "ID": null,
      "Description": "Increases the duration time of Universal Judgement by 12 seconds. Reduces 6% more damage taking.",
      "Lore": null,
      "Level": 6,
      "Type": "Aura",
      "CastTime": null,
      "Vigor Cost": null,
      "ManaCost": null,
      "CoolDown": null,
      "Duration": null
    },
    {
      "Name": "Holy Whisper",
      "Class": "Templar",
      "ID": null,
      "Description": "Damage Addition: 120%. Adds 648 damage to a successful hit.",
      "Lore": "Instantly recovers great amount of HP for a target. In the next 10 seconds, recovers some extra HP per 2 seconds.",
      "Level": 6,
      "Type": "Single Healing",
      "CastTime": "2 seconds",
      "Vigor Cost": null,
      "ManaCost": 1461,
      "CoolDown": "1 second",
      "Duration": null
    },
    {
      "Name": "Tortoise Fortify",
      "Class": "Templar",
      "ID": null,
      "Description": "Increases the healing effect of Holy Whisper by 120%.",
      "Lore": null,
      "Level": 6,
      "Type": "Aura",
      "CastTime": null,
      "Vigor Cost": null,
      "ManaCost": null,
      "CoolDown": null,
      "Duration": null
    },
    {
      "Name": "Resonane",
      "Class": "Templar",
      "ID": null,
      "Description": "Recovers HP as 115.0% of the Templar's INT. Both yourself and your target will receive this.",
      "Lore": null,
      "Level": 5,
      "Type": "Single Healing",
      "CastTime": "2 seconds",
      "Vigor Cost": null,
      "ManaCost": 512,
      "CoolDown": "1 second",
      "Duration": null
    },
    {
      "Name": "God's Blessing",
      "Class": "Templar",
      "ID": null,
      "Description": "Recovers the HP of all group members within 11 meters at 140.0% of the Templar's INT over 10 seconds. This effect can be stacked up to 5 times.",
      "Lore": null,
      "Level": 5,
      "Type": "Group Healing",
      "CastTime": "2 seconds",
      "Vigor Cost": null,
      "ManaCost": 865,
      "CoolDown": "1 second",
      "Duration": null
    },
    {
      "Name": "Blood Aura",
      "Class": "Heretic",
      "ID": null,
      "Description": "Increases the healing effect of all friendly units within 15 yards by 12% and increases own Ferus Resistance by 18.",
      "Lore": null,
      "Level": 6,
      "Type": "Aura",
      "CastTime": "10 seconds",
      "Vigor Cost": null,
      "ManaCost": 4500,
      "CoolDown": "300 seconds",
      "Duration": null
    },
    {
      "Name": "Wind Fortify",
      "Class": "Heretic",
      "ID": null,
      "Description": "Increases the effect of Blood Aura. The aura can increases 18 more own Resistance.",
      "Lore": null,
      "Level": 6,
      "Type": "Aura",
      "CastTime": null,
      "Vigor Cost": null,
      "ManaCost": null,
      "CoolDown": null,
      "Duration": null
    },
    {
      "Name": "Shock Bolt",
      "Class": "Heretic",
      "ID": null,
      "Description": "Damage Addition: 120.%. Adds 558 damage upon a successful hit.",
      "Lore": "Reduces target Vigor by 60.",
      "Level": 6,
      "Type": "Flora Spell",
      "CastTime": "1 second",
      "Vigor Cost": null,
      "ManaCost": 457,
      "CoolDown": "6 seconds",
      "Duration": null
    },
    {
      "Name": "Phoenix Fortify",
      "Class": "Heretic",
      "ID": null,
      "Description": "Increases the additional damage of Shock Bolt by 12% and Vigor reduction by 30.",
      "Lore": null,
      "Level": 6,
      "Type": "Aura",
      "CastTime": null,
      "Vigor Cost": null,
      "ManaCost": null,
      "CoolDown": null,
      "Duration": null
    },
    {
      "Name": "Vacuum Explosion",
      "Class": "Heretic",
      "ID": null,
      "Description": "Damage Addition: 120.0%. Adds 558 damage upon a successful hit.",
      "Lore": "Deals great damage to target and reduce target's Mana by 24% if it has been hit by Shock Bolt.",
      "Level": 6,
      "Type": "Flora Spell",
      "CastTime": "1 second",
      "Vigor Cost": null,
      "ManaCost": 513,
      "CoolDown": "6 seconds",
      "Duration": null
    },
    {
      "Name": "Serpent Fortify",
      "Class": "Heretic",
      "ID": null,
      "Description": "Increases the effect of Vacuum Explosion. Increases additional damage by 12% and Mana reduction by 18%.",
      "Lore": null,
      "Level": 6,
      "Type": "Aura",
      "CastTime": null,
      "Vigor Cost": null,
      "ManaCost": null,
      "CoolDown": null,
      "Duration": null
    },
    {
      "Name": "Blood Manager",
      "Class": "Heretic",
      "ID": null,
      "Description": "Increases the Critstrike rates of all group members within 11 meters over the next 60 seconds by 15%.",
      "Lore": null,
      "Level": 5,
      "Type": "Allies Blessing",
      "CastTime": "2 seconds",
      "Vigor Cost": null,
      "ManaCost": 865,
      "CoolDown": "120 seconds",
      "Duration": null
    },
    {
      "Name": "Flora Demon",
      "Class": "Heretic",
      "ID": null,
      "Description": "Deals 200% basic damage. Increases the target's damage by 100% if it has been hit by Shock Bolt. This damage is unrelated to Elemental Points or Elemental Resistance.",
      "Lore": null,
      "Level": 5,
      "Type": "Flora Spell",
      "CastTime": "2 seconds",
      "Vigor Cost": null,
      "ManaCost": 512,
      "CoolDown": "6 seconds",
      "Duration": null
    },
    {
      "Name": "Cascade Maneuver",
      "Class": "Pyromancer",
      "ID": null,
      "Description": "Increases Critcast damage by 24%. While active, 5% of incoming damage will be deducted from your mana points.",
      "Lore": null,
      "Level": 6,
      "Type": "Aura",
      "CastTime": "10 seconds",
      "Vigor Cost": null,
      "ManaCost": 4500,
      "CoolDown": "300 seconds",
      "Duration": null
    },
    {
      "Name": "Solar Positivity",
      "Class": "Pyromancer",
      "ID": null,
      "Description": "Cascade Maneuver receive an additional 24% to critcast damage.",
      "Lore": null,
      "Level": 6,
      "Type": "Aura",
      "CastTime": null,
      "Vigor Cost": null,
      "ManaCost": null,
      "CoolDown": null,
      "Duration": null
    },
    {
      "Name": "Omni Lamp",
      "Class": "Pyromancer",
      "ID": null,
      "Description": "Damage Addition: 206%. Adds 1124 damage upon a successful hit.",
      "Lore": "Damages target and adds an extra 120.0% INT damage over 10 seconds. Stacks up to 6 times.",
      "Level": 6,
      "Type": "Pyros Spell",
      "CastTime": "2 seconds",
      "Vigor Cost": null,
      "ManaCost": 794,
      "CoolDown": "0 seconds",
      "Duration": null
    },
    {
      "Name": "Solar Brightness",
      "Class": "Pyromancer",
      "ID": null,
      "Description": "Omni Lamp deals 12% more extra damage.",
      "Lore": null,
      "Level": 6,
      "Type": "Aura",
      "CastTime": null,
      "Vigor Cost": null,
      "ManaCost": null,
      "CoolDown": null,
      "Duration": null
    },
    {
      "Name": "Inferno Scream",
      "Class": "Pyromancer",
      "ID": null,
      "Description": "For 15 seconds, each successful Omni Lamp cast will increase 6% critcast rate and 6% critcast damage. Stacks up to 10 times. Lasts for 30 seconds and drains 10% of Mana per second after the first Lamp cast.",
      "Lore": null,
      "Level": 6,
      "Type": "Self-Blessing",
      "CastTime": "2 seconds",
      "Vigor Cost": null,
      "ManaCost": 794,
      "CoolDown": "180 seconds",
      "Duration": null
    },
    {
      "Name": "Solar Brightness",
      "Class": "Pyromancer",
      "ID": null,
      "Description": "Inferno Scream receive an additional 6% increase to critcast rate and 6% more critcast damage.",
      "Lore": null,
      "Level": 6,
      "Type": "Aura",
      "CastTime": null,
      "Vigor Cost": null,
      "ManaCost": null,
      "CoolDown": null,
      "Duration": null
    },
    {
      "Name": "Warfire",
      "Class": "Pyromancer",
      "ID": null,
      "Description": "Deals 160% INT damage. Each Omni Lamp on the target will increase this effect by 40%. This damage is unrelated to Elemental Points or Elemental Resistance.",
      "Lore": null,
      "Level": 5,
      "Type": "Pyros Spell",
      "CastTime": "1 second",
      "Vigor Cost": null,
      "ManaCost": 512,
      "CoolDown": "10 seconds",
      "Duration": null
    },
    {
      "Name": "Pyros Blessing",
      "Class": "Pyromancer",
      "ID": null,
      "Description": "Increases your Movement Speed by 4.5 m/s. Increases Pyros Affinity by 60 for 30 seconds.",
      "Lore": null,
      "Level": 5,
      "Type": "Self-Blessing",
      "CastTime": "1 second",
      "Vigor Cost": null,
      "ManaCost": 512,
      "CoolDown": "225 seconds",
      "Duration": null
    },
    {
      "Name": "Lunar Cycle",
      "Class": "Tempest",
      "ID": null,
      "Description": "Increases Critcast rate by 6% and Max Mana by 18%.",
      "Lore": null,
      "Level": 6,
      "Type": "Aura",
      "CastTime": "10 seconds",
      "Vigor Cost": null,
      "ManaCost": 4500,
      "CoolDown": "300 seconds",
      "Duration": null
    },
    {
      "Name": "Extreme Negation",
      "Class": "Tempest",
      "ID": null,
      "Description": "Lunar Cycle receive and additional 6% critcast rate and -glitched #- more Max Mana.",
      "Lore": null,
      "Level": 6,
      "Type": "Aura",
      "CastTime": null,
      "Vigor Cost": null,
      "ManaCost": null,
      "CoolDown": null,
      "Duration": null
    },
    {
      "Name": "Ocean Sovereign",
      "Class": "Tempest",
      "ID": null,
      "Description": "Transfers 60.0% current mana to damage output. Has a chance to deal double damage to target if it has been hit by Fleece Charm.",
      "Lore": null,
      "Level": 6,
      "Type": "Aquan Spell",
      "CastTime": "3 seconds",
      "Vigor Cost": null,
      "ManaCost": "60%",
      "CoolDown": "60 seconds",
      "Duration": null
    },
    {
      "Name": "Extreme Degeneration",
      "Class": "Tempest",
      "ID": null,
      "Description": "Ocean Sovereign uses and additional 30% mana to convert into damage.",
      "Lore": null,
      "Level": 6,
      "Type": "Aura",
      "CastTime": null,
      "Vigor Cost": null,
      "ManaCost": null,
      "CoolDown": null,
      "Duration": null
    },
    {
      "Name": "Glacial Galaxy",
      "Class": "Tempest",
      "ID": null,
      "Description": "Damage Addition: 120.0%. Freeze massive targets within 9 yards for 9 seconds.",
      "Lore": null,
      "Level": 6,
      "Type": "Aquan Spell",
      "CastTime": "1 second",
      "Vigor Cost": null,
      "ManaCost": 794,
      "CoolDown": "30 seconds",
      "Duration": null
    },
    {
      "Name": "Extreme Passivity",
      "Class": "Tempest",
      "ID": null,
      "Description": "Increases the freeze time of Glacial Galaxy by 6 seconds and reduces it cooldown by 6 seconds.",
      "Lore": null,
      "Level": 6,
      "Type": "Aura",
      "CastTime": null,
      "Vigor Cost": null,
      "ManaCost": null,
      "CoolDown": null,
      "Duration": null
    },
    {
      "Name": "Ice Protection",
      "Class": "Tempest",
      "ID": null,
      "Description": "Creates a magic barrier, up to 160% of your INT can be absorbed. Slows all targets within 5 meters by 2.5 m/s. Lasts for a maximum of 30 seconds.",
      "Lore": null,
      "Level": 5,
      "Type": "Self-Blessing",
      "CastTime": null,
      "Vigor Cost": null,
      "ManaCost": 512,
      "CoolDown": "225 seconds",
      "Duration": null
    },
    {
      "Name": "Ice Break",
      "Class": "Tempest",
      "ID": null,
      "Description": "Deals 160% spell damage with extreme cold. Increases target's damage by 100% if it has been hit by Glacial Galaxy. This damage is unrelated to Elemental Points or Elemental Resistance.",
      "Lore": null,
      "Level": 5,
      "Type": "Group Aquan Spell",
      "CastTime": "1 second",
      "Vigor Cost": null,
      "ManaCost": 512,
      "CoolDown": "15 seconds",
      "Duration": null
    },
    {
      "Name": "Mercy Shrine",
      "Class": "Priest",
      "ID": null,
      "Description": "Increases own Healing effect by 12%.",
      "Lore": null,
      "Level": 6,
      "Type": "Aura",
      "CastTime": "10 seconds",
      "Vigor Cost": null,
      "ManaCost": 4500,
      "CoolDown": "300 seconds",
      "Duration": null
    },
    {
      "Name": "Total Inspiration",
      "Class": "Priest",
      "ID": null,
      "Description": "Increases the healing effect of Mercy Shrine by 12%.",
      "Lore": null,
      "Level": 6,
      "Type": "Aura",
      "CastTime": null,
      "Vigor Cost": null,
      "ManaCost": null,
      "CoolDown": null,
      "Duration": null
    },
    {
      "Name": "Incantation Glow",
      "Class": "Priest",
      "ID": null,
      "Description": "INT Use: 120.0%. Absorbs: 1087.",
      "Lore": "Uses INT plus and additional amount to create a protective barrier.",
      "Level": 6,
      "Type": "Single Blessing",
      "CastTime": "1 second",
      "Vigor Cost": null,
      "ManaCost": 1230,
      "CoolDown": "5 seconds",
      "Duration": "14 seconds"
    },
    {
      "Name": "Total Enlightenment",
      "Class": "Priest",
      "ID": null,
      "Description": "Icantation Glow's aura increases damage protection by 30% of your INT.",
      "Lore": null,
      "Level": 6,
      "Type": "Aura",
      "CastTime": null,
      "Vigor Cost": null,
      "ManaCost": null,
      "CoolDown": null,
      "Duration": null
    },
    {
      "Name": "Sincere Chant",
      "Class": "Priest",
      "ID": null,
      "Description": "Completely recovers you to full health. Available while Silenced or Stunned. Higher grades means lower mana costs and shorter cooldown.",
      "Lore": null,
      "Level": 6,
      "Type": "Self-Blessing",
      "CastTime": "1 second",
      "Vigor Cost": null,
      "ManaCost": 397,
      "CoolDown": "200 seconds",
      "Duration": null
    },
    {
      "Name": "Total Abstinency",
      "Class": "Priest",
      "ID": null,
      "Description": "Besides healing, Sincere Chant has a 90% chance to dispell own negative stauts.",
      "Lore": null,
      "Level": 6,
      "Type": "Aura",
      "CastTime": null,
      "Vigor Cost": null,
      "ManaCost": null,
      "CoolDown": null,
      "Duration": null
    },
    {
      "Name": "Array Glow",
      "Class": "Priest",
      "ID": null,
      "Description": "Damage Addition: 115.0%. Absorbs 996.",
      "Lore": "Creates an aura that absorbs damage for 20 friendly targets over the next 15 seconds.",
      "Level": 5,
      "Type": "Allies Blessing",
      "CastTime": "1 second",
      "Vigor Cost": null,
      "ManaCost": 1472,
      "CoolDown": "15 seconds",
      "Duration": null
    },
    {
      "Name": "Banning Curse",
      "Class": "Priest",
      "ID": null,
      "Description": "Silences all targets within 6 meters. Lasts 7 seconds and prevents them from eating for 3.5 seconds. Useable while under the Silenve and Stun effect.",
      "Lore": null,
      "Level": 5,
      "Type": "Group Curse",
      "CastTime": null,
      "Vigor Cost": null,
      "ManaCost": 512,
      "CoolDown": "60 seconds",
      "Duration": null
    },
    {
      "Name": "Fatal Comprehension",
      "Class": "Shura",
      "ID": null,
      "Description": "Reduces spell damage received by 6% and reduces the healing effect of Divine Radiance by 12%.",
      "Lore": null,
      "Level": 6,
      "Type": "Aura",
      "CastTime": "10 seconds",
      "Vigor Cost": null,
      "ManaCost": 4500,
      "CoolDown": "300 seconds",
      "Duration": null
    },
    {
      "Name": "Total Humiliation",
      "Class": "Shura",
      "ID": null,
      "Description": "Fatal Comprehension reduces incoming spell damage by an additional 6% but also reduces the healing effect of Divine Radiance by and additional 12%.",
      "Lore": null,
      "Level": 6,
      "Type": "Aura",
      "CastTime": null,
      "Vigor Cost": null,
      "ManaCost": null,
      "CoolDown": null,
      "Duration": null
    },
    {
      "Name": "Shura's Decision",
      "Class": "Shura",
      "ID": null,
      "Description": "Damage Addition: 206%. Basic Damage: 1087.",
      "Lore": "Deals constant damage to a single target over 20 seconds.",
      "Level": 6,
      "Type": "Aquan Curse",
      "CastTime": "2 seconds",
      "Vigor Cost": null,
      "ManaCost": 819,
      "CoolDown": "2 seconds",
      "Duration": null
    },
    {
      "Name": "Total Forgiveness",
      "Class": "Shura",
      "ID": null,
      "Description": "Increases the bleed damage of Shura's Decision by 12%.",
      "Lore": null,
      "Level": 6,
      "Type": "Aura",
      "CastTime": null,
      "Vigor Cost": null,
      "ManaCost": null,
      "CoolDown": null,
      "Duration": null
    },
    {
      "Name": "Blink Hellhounds",
      "Class": "Shura",
      "ID": null,
      "Description": "Damage Addition: 137%. Basic Damage: 602,",
      "Lore": "Deals 50% damage and reduces the target's mana based on your own INT.",
      "Level": 6,
      "Type": "Aquan Spell",
      "CastTime": "2 seconds",
      "Vigor Cost": null,
      "ManaCost": 819,
      "CoolDown": "2 seconds",
      "Duration": null
    },
    {
      "Name": "Total Devotion",
      "Class": "Shura",
      "ID": null,
      "Description": "Blink Hellhounds burns 12% more mana.",
      "Lore": null,
      "Level": 6,
      "Type": "Aura",
      "CastTime": null,
      "Vigor Cost": null,
      "ManaCost": null,
      "CoolDown": null,
      "Duration": null
    },
    {
      "Name": "Demon's Hatred",
      "Class": "Shura",
      "ID": null,
      "Description": "Deals 160% spell damage. Reduces the target's speed by 7 m/s for 15 seconds if it has been hit by Shura's Decision.",
      "Lore": null,
      "Level": 5,
      "Type": "Aquan Curse",
      "CastTime": "1 second",
      "Vigor Cost": null,
      "ManaCost": 512,
      "CoolDown": "6 seconds",
      "Duration": null
    },
    {
      "Name": "Devil's Curse",
      "Class": "Shura",
      "ID": null,
      "Description": "Deals 160% spell damage. Recovers HP as 80% of INT.",
      "Lore": null,
      "Level": 5,
      "Type": "Aquan Curse",
      "CastTime": "1 second",
      "Vigor Cost": null,
      "ManaCost": 512,
      "CoolDown": "6 seconds",
      "Duration": null
    }
  ]